SEVtras/__init__.py
SEVtras/_docs.py
SEVtras/env.py
SEVtras/evs.gmt
SEVtras/evsM.gmt
SEVtras/functional.py
SEVtras/id_homo_rna_ev
SEVtras/id_mus_rna_ev
SEVtras/main.py
SEVtras/sc_pp.py
SEVtras/sc_readwrite.py
SEVtras/sc_utils.py
SEVtras/utils.py
SEVtras/version.py
SEVtras-0.2.13.dist-info/LICENSE
SEVtras-0.2.13.dist-info/METADATA
SEVtras-0.2.13.dist-info/WHEEL
SEVtras-0.2.13.dist-info/entry_points.txt
SEVtras-0.2.13.dist-info/top_level.txt
SEVtras-0.2.13.dist-info/RECORD
