Metadata-Version: 2.1
Name: SEVtras
Version: 0.2.13
Summary: sEV-containing droplet identification in scRNA-seq data
Home-page: http://pypi.python.org/pypi/SEVtras/
Author: Ruiqiao He
Author-email: ruiqiaohe@gmail.com
License: GPL
Classifier: Development Status :: 3 - Alpha
Classifier: License :: OSI Approved :: GNU General Public License v3 (GPLv3)
Classifier: Programming Language :: Python :: 3
Classifier: Programming Language :: Python :: 3.7
Classifier: Programming Language :: Python :: 3.8
Classifier: Programming Language :: Python :: 3.9
Classifier: Programming Language :: Python :: 3.10
Classifier: Programming Language :: Python :: 3.11
Classifier: Topic :: Scientific/Engineering :: Bio-Informatics
Requires-Python: >=3.7.1
License-File: LICENSE
Requires-Dist: numpy <2.0.0,>=1.21.5
Requires-Dist: pandas <2.2.0,>=1.1.2
Requires-Dist: scipy <1.13.1,>=1.5.4
Requires-Dist: statsmodels <0.14.4,>=0.12.1
Requires-Dist: anndata <0.11.1,>=0.7.4
Requires-Dist: gseapy ==0.14.0
Requires-Dist: umap-learn ==0.5.3
